{
       "J-coupling": [
                       {
                            "ID2": 8,
                            "ID1": 7,
                          "value": -11.7569
                       },
                       {
                            "ID2": 11,
                            "ID1": 7,
                          "value": 4.3145
                       },
                       {
                            "ID2": 11,
                            "ID1": 8,
                          "value": 6.5125
                       },
                       {
                            "ID2": 9,
                            "ID1": 11,
                          "value": 4.314484
                       },
                       {
                            "ID2": 10,
                            "ID1": 11,
                          "value": 6.512546
                       },
                       {
                            "ID2": 10,
                            "ID1": 9,
                          "value": -11.75689
                       }
                     ],
   "chemical shift": [
                       {
                          "value": 3.6387,
                             "ID": 7
                       },
                       {
                          "value": 3.5481,
                             "ID": 8
                       },
                       {
                          "value": 3.77118,
                             "ID": 11
                       },
                       {
                          "value": 3.63872,
                             "ID": 9
                       },
                       {
                          "value": 3.54807,
                             "ID": 10
                       }
                     ]
}
