{
       "J-coupling": [
                       {
                            "ID2": 16,
                            "ID1": 14,
                          "value": 7.710751
                       },
                       {
                            "ID2": 18,
                            "ID1": 14,
                          "value": 7.875915
                       },
                       {
                            "ID2": 20,
                            "ID1": 16,
                          "value": 7.710751
                       },
                       {
                            "ID2": 15,
                            "ID1": 19,
                          "value": 7.875915
                       },
                       {
                            "ID2": 17,
                            "ID1": 15,
                          "value": 7.710751
                       },
                       {
                            "ID2": 21,
                            "ID1": 17,
                          "value": 7.710751
                       }
                     ],
   "chemical shift": [
                       {
                          "value": 7.1789,
                             "ID": 14
                       },
                       {
                          "value": 7.3862,
                             "ID": 16
                       },
                       {
                          "value": 7.5121,
                             "ID": 20
                       },
                       {
                          "value": 8.1164,
                             "ID": 18
                       },
                       {
                          "value": 8.1164,
                             "ID": 19
                       },
                       {
                          "value": 7.1789,
                             "ID": 15
                       },
                       {
                          "value": 7.3862,
                             "ID": 17
                       },
                       {
                          "value": 7.5121,
                             "ID": 21
                       }
                     ]
}
