{
       "J-coupling": [
                       {
                            "ID2": 10,
                            "ID1": 9,
                          "value": 11.300886
                       },
                       {
                            "ID2": 12,
                            "ID1": 11,
                          "value": 11.300886
                       }
                     ],
   "chemical shift": [
                       {
                          "value": 6.79963,
                             "ID": 9
                       },
                       {
                          "value": 6.79963,
                             "ID": 10
                       },
                       {
                          "value": 6.79963,
                             "ID": 11
                       },
                       {
                          "value": 6.79963,
                             "ID": 12
                       }
                     ]
}
