{
       "J-coupling": [
                       {
                            "ID2": 9,
                            "ID1": 11,
                          "value": 8.499108
                       },
                       {
                            "ID2": 10,
                            "ID1": 11,
                          "value": 0.967271
                       },
                       {
                            "ID2": 12,
                            "ID1": 11,
                          "value": 0.556498
                       },
                       {
                            "ID2": 10,
                            "ID1": 9,
                          "value": 0.556498
                       },
                       {
                            "ID2": 12,
                            "ID1": 9,
                          "value": 0.967271
                       },
                       {
                            "ID2": 12,
                            "ID1": 10,
                          "value": 8.499108
                       }
                     ],
   "chemical shift": [
                       {
                          "value": 6.78079,
                             "ID": 11
                       },
                       {
                          "value": 6.77022,
                             "ID": 9
                       },
                       {
                          "value": 6.78079,
                             "ID": 10
                       },
                       {
                          "value": 6.77022,
                             "ID": 12
                       }
                     ]
}
