{
       "J-coupling": [
                       {
                            "ID2": 24,
                            "ID1": 23,
                          "value": 0.4
                       },
                       {
                            "ID2": 22,
                            "ID1": 21,
                          "value": -14
                       },
                       {
                            "ID2": 25,
                            "ID1": 21,
                          "value": 8.529732
                       },
                       {
                            "ID2": 25,
                            "ID1": 22,
                          "value": 4.535358
                       },
                       {
                            "ID2": 18,
                            "ID1": 17,
                          "value": -16.7588
                       },
                       {
                            "ID2": 19,
                            "ID1": 17,
                          "value": 7.006505
                       },
                       {
                            "ID2": 20,
                            "ID1": 17,
                          "value": 7.006505
                       },
                       {
                            "ID2": 19,
                            "ID1": 18,
                          "value": 7.006505
                       },
                       {
                            "ID2": 20,
                            "ID1": 18,
                          "value": 7.006505
                       },
                       {
                            "ID2": 20,
                            "ID1": 19,
                          "value": -14
                       }
                     ],
   "chemical shift": [
                       {
                          "value": 7.0523,
                             "ID": 23
                       },
                       {
                          "value": 8.0156,
                             "ID": 24
                       },
                       {
                          "value": 3.0154,
                             "ID": 21
                       },
                       {
                          "value": 3.1654,
                             "ID": 22
                       },
                       {
                          "value": 4.46473,
                             "ID": 25
                       },
                       {
                          "value": 2.69065,
                             "ID": 17
                       },
                       {
                          "value": 2.65426,
                             "ID": 18
                       },
                       {
                          "value": 3.226,
                             "ID": 19
                       },
                       {
                          "value": 3.18847,
                             "ID": 20
                       }
                     ]
}
