{
       "J-coupling": [
                       {
                            "ID2": 10,
                            "ID1": 9,
                          "value": -14.899999
                       },
                       {
                            "ID2": 11,
                            "ID1": 9,
                          "value": -14.899999
                       },
                       {
                            "ID2": 14,
                            "ID1": 9,
                          "value": 1
                       },
                       {
                            "ID2": 13,
                            "ID1": 9,
                          "value": 1
                       },
                       {
                            "ID2": 11,
                            "ID1": 10,
                          "value": -14.899999
                       },
                       {
                            "ID2": 14,
                            "ID1": 10,
                          "value": 1
                       },
                       {
                            "ID2": 13,
                            "ID1": 10,
                          "value": 1
                       },
                       {
                            "ID2": 14,
                            "ID1": 11,
                          "value": 1
                       },
                       {
                            "ID2": 13,
                            "ID1": 11,
                          "value": 1
                       },
                       {
                            "ID2": 15,
                            "ID1": 14,
                          "value": 8.334962
                       },
                       {
                            "ID2": 13,
                            "ID1": 14,
                          "value": 2.301216
                       },
                       {
                            "ID2": 12,
                            "ID1": 15,
                          "value": 2.301216
                       },
                       {
                            "ID2": 13,
                            "ID1": 12,
                          "value": 8.334962
                       }
                     ],
   "chemical shift": [
                       {
                          "value": 2.2473,
                             "ID": 9
                       },
                       {
                          "value": 2.2473,
                             "ID": 10
                       },
                       {
                          "value": 2.2473,
                             "ID": 11
                       },
                       {
                          "value": 7.13178,
                             "ID": 14
                       },
                       {
                          "value": 6.81819,
                             "ID": 15
                       },
                       {
                          "value": 6.81819,
                             "ID": 12
                       },
                       {
                          "value": 7.13178,
                             "ID": 13
                       }
                     ]
}
